MANIFEST.in
README.rst
setup.py
AnyFilter.egg-info/PKG-INFO
AnyFilter.egg-info/SOURCES.txt
AnyFilter.egg-info/dependency_links.txt
AnyFilter.egg-info/not-zip-safe
AnyFilter.egg-info/top_level.txt
anyfilter/__init__.py