Metadata-Version: 1.0
Name: AnyFilter
Version: 0.02
Summary: Base class for easy filtering of iterable of dictionaries.
Home-page: https://github.com/ShawnMilo/anyfilter
Author: Shawn Milochik
Author-email: shawn@milochik.com
License: BSD
Keywords: dictionary filter dict json
Platform: UNKNOWN
